{"version":2,"settings":{"scope":"global","projectSettings":{"pagesOn":true,"defaults":{"pageName":"Page","sectionTitle":"Section","sectionText":"This is a section, and inside of it you can placechoices      On both Sections and Choices, Requirements can be placed, which will      block a      Section from being shown or make the player unable to select a choice,      respectively.","idLength":5}},"pagesOn":true},"state":{"currentPage":1,"activatedChoices":[],"allIds":{}},"styling":{"scope":"global","choices":{"changeBackgroundColourOnSelect":true,"backgroundColourOnSelect":"#CFFAA7","changeTextColourOnSelect":false,"changeBackgroundColourOnHover":false,"changeTextColourOnHover":false}},"pages":[{"id":"main","type":"page","pageName":"CYOA","settings":{"scope":"page"},"pageItems":[{"type":"section","id":"row1","title":"First Row","text":"This is my first Row","editModeEnabled":false,"choices":[],"settings":{"scope":"section"}},{"type":"divider","id":"9f7s","editModeEnabled":false,"settings":{"scope":"pageItem"}},{"type":"section","id":"row3","title":"Perks","text":"Pick any Perks you would like.","editModeEnabled":false,"settings":{"scope":"section"},"choices":[{"id":"sk92","type":"choice","title":"Forever Memory","text":"You now have perfect memory. You will never forget a\nmemory. This works retroactively too.","settings":{"scope":"choice"}},{"id":"k9f2","type":"choice","title":"Body of Atlas","text":"You have unlimited stamina. You can lift up to 50 million\ntimes more than a regular human.","settings":{"scope":"choice"}},{"id":"09r2","type":"choice","title":"Avalon","text":"Your body's healing is greater than anyone before you.\nYou regenerate nigh-instantly.","settings":{"scope":"choice"}}]}]},{"id":"second","type":"page","pageName":"Second page","settings":{"scope":"page"},"pageItems":[{"type":"section","id":"row2","title":"Second row","text":"This is my second row. Teehee!","editModeEnabled":false,"choices":[],"settings":{"scope":"section"}}]}]}